radexreader/__init__.py
radexreader/radexreader-cli.py
radexreader-1.3.0.dist-info/licenses/LICENSE
radexreader-1.3.0.dist-info/METADATA
radexreader-1.3.0.dist-info/WHEEL
radexreader-1.3.0.dist-info/top_level.txt
radexreader-1.3.0.dist-info/RECORD
