Metadata-Version: 2.4
Name: radexreader
Version: 1.3.0
Summary: Python library for the RADEX RD1212 and the RADEX ONE Geiger counters.
Home-page: https://github.com/luigifab/python-radexreader
Author: Fabrice Creuzot
Author-email: code@luigifab.fr
License: GPL 2
License-File: LICENSE
Requires-Dist: pyusb
Requires-Dist: pyserial
Dynamic: author
Dynamic: author-email
Dynamic: description
Dynamic: description-content-type
Dynamic: home-page
Dynamic: license
Dynamic: license-file
Dynamic: requires-dist
Dynamic: summary
